itchcraft/__init__.py
itchcraft/__main__.py
itchcraft/api.py
itchcraft/backend.py
itchcraft/cli.py
itchcraft/device.py
itchcraft/devices.py
itchcraft/errors.py
itchcraft/fire_workarounds.py
itchcraft/format.py
itchcraft/heat_it.py
itchcraft/logging.py
itchcraft/prefs.py
itchcraft/settings.py
itchcraft/start.py
itchcraft/stubs/usb/backend.pyi
itchcraft/stubs/usb/core.pyi
itchcraft/stubs/usb/util.pyi
itchcraft/support.py
itchcraft/types/__init__.py
itchcraft/types/usb.py
itchcraft/version.py
itchcraft-0.4.1.dist-info/LICENSE
itchcraft-0.4.1.dist-info/METADATA
itchcraft-0.4.1.dist-info/WHEEL
itchcraft-0.4.1.dist-info/entry_points.txt
itchcraft-0.4.1.dist-info/RECORD
