Metadata-Version: 2.1
Name: itchcraft
Version: 0.4.1
Summary: Tech demo for interfacing with heat-based USB insect bite healers
License: Apache-2.0
Author: Claudia Pellegrino
Author-email: clau@tiqua.de
Requires-Python: >=3.9
Classifier: Development Status :: 3 - Alpha
Classifier: License :: OSI Approved :: Apache Software License
Classifier: Operating System :: POSIX :: Linux
Classifier: Programming Language :: Python :: 3
Classifier: Programming Language :: Python :: 3.9
Classifier: Programming Language :: Python :: 3.10
Classifier: Programming Language :: Python :: 3.11
Classifier: Programming Language :: Python :: 3.12
Classifier: Topic :: Utilities
Requires-Dist: colorama
Requires-Dist: fire
Requires-Dist: pyusb (>=1.0.2,<2.0.0)
Requires-Dist: tenacity (>=6.2.0,<7.0.0)
